disrider/__init__.py
disrider/disrider.py
disrider-1.0.4.dist-info/METADATA
disrider-1.0.4.dist-info/WHEEL
disrider-1.0.4.dist-info/top_level.txt
disrider-1.0.4.dist-info/RECORD
